pytest_quickify.py
pytest_quickify-0.1.0.dist-info/LICENSE
pytest_quickify-0.1.0.dist-info/WHEEL
pytest_quickify-0.1.0.dist-info/METADATA
pytest_quickify-0.1.0.dist-info/RECORD
