Metadata-Version: 2.1
Name: pytest_quickify
Version: 0.1.0
Summary: Run test suites with pytest-quickify.
Home-page: https://github.com/testprogress/pytest-quickify
License: UNKNOWN
Author: Madelyn Kapfhammer
Author-email: maddy.kapfhammer@gmail.com
Maintainer: MaddyKapfhammer
Maintainer-email: maddy.kapfhammer@gmail.com
Requires-Python: >=3.6
Classifier: Programming Language :: Python :: 3.6
Classifier: Intended Audience :: Developers
Classifier: License :: OSI Approved :: GNU General Public License (GPL)
Classifier: Topic :: Documentation
Classifier: Topic :: Software Development :: Documentation
Classifier: Topic :: Software Development :: Quality Assurance
Requires-Dist: pytest
